kea_bigquery_connection
