Metadata-Version: 1.0
Name: kea-bigquery-connection
Version: 1.2
Summary: Run queries in bigquery and get a data response
Home-page: http://kea.mx/
Author: Daniel Hernández
Author-email: dhernandez@kea.mx
License: MIT
Platform: UNKNOWN
